Workbook
Name SIM_NAO: LISTAS!$A$5:$A$6
Name UF: LISTAS!$B$5:$B$31
Name TITDEP: LISTAS!$C$5:$C$6
Name CAT_REND: LISTAS!$D$5:$D$14
Name GRUPO_BENS: LISTAS!$E$5:$E$11
Name TIPO_DIVIDA: LISTAS!$F$5:$F$10
Name CAT_PAG: LISTAS!$G$5:$G$12
Name PARENTESCO: LISTAS!$H$5:$H$12
Name STATUS_DOC: LISTAS!$I$5:$I$9
Name CAT_DOC: LISTAS!$J$5:$J$11
Name OCUPACAO: LISTAS!$K$5:$K$11
Name BANCOS: LISTAS!$L$5:$L$20

Sheet INICIO
B2: AGREGADOR DE
B3: IMPOSTO DE RENDA
B5: Organizador de dados para a Declaracao de IRPF - Pessoa Fisica
B6: Desafio DIO | Microsoft Excel
B8: COMO USAR
B9: 1. Comece pela aba DADOS PESSOAIS e preencha a identificacao do contribuinte.
B10: 2. Registre suas informacoes nas abas de RENDIMENTOS, BENS, DIVIDAS e PAGAMENTOS.
B11: 3. Cadastre seus DEPENDENTES e controle os COMPROVANTES na aba DOCUMENTOS.
B12: 4. Acompanhe os totais consolidados na aba RESUMO (dashboard).
B13: 5. Prefira sempre os menus suspensos; campos com * sao obrigatorios.
B15: MENU DE NAVEGACAO
B16: 1 Dados Pessoais | C16: 2 Rendimentos | D16: 3 Bens e Direitos
B18: 4 Dividas e Onus | C18: 5 Pagamentos / Despesas | D18: 6 Dependentes
B20: 7 Documentos | C20: 8 Resumo (Dashboard)
B23: LINKS RAPIDOS (sites oficiais)
B24: Portal e-CAC - Receita Federal
B25: Programa IRPF / Meu Imposto de Renda
B26: Consulta CPF / Situacao cadastral
B27: Perguntas e respostas IRPF
B29: Versao 1.0 - Os dados de exemplo sao ficticios e servem apenas para demonstracao.
B30: Autor: Bel | Projeto do desafio DIO

Sheet DADOS PESSOAIS
B1: AGREGADOR DE IMPOSTO DE RENDA | F1: Inicio
B2: 1. DADOS PESSOAIS
B4: Identificacao do contribuinte (titular). Campos com * sao obrigatorios.
B6: Nome completo * | E6: MARIA FICTICIA DA SILVA
B7: CPF * | E7: 111.444.777-35
B8: Data de nascimento * | E8: 10/05/1990
B9: Idade | C9: =IFERROR(DATEDIF(C7,TODAY(),"y"),"") | E9: (auto)
B10: Titulo de eleitor | E10: 1234567890 SP
B11: Nome da mae | E11: JOANA FICTICIA
B12: Ocupacao principal | E12: Autonomo(a) / MEI
B13: E-mail | E13: maria.exemplo@email.com
B14: Telefone / Celular | E14: (11) 99999-0000
B15: CEP | E15: 01310-100
B16: Logradouro (rua, av.) | E16: Av. das Demonstracoes
B17: Numero | E17: 1000
B18: Complemento | E18: Sala 5
B19: Bairro | E19: Centro
B20: Cidade | E20: Sao Paulo
B21: UF | E21: SP
... B25: Residente no exterior? | E25: Nao
B27: * Preencha antes de iniciar a declaracao no programa da Receita. O CPF e a data de nascimento sao obrigatorios para o acesso ao e-CAC.

Sheet RENDIMENTOS
B1: AGREGADOR DE IMPOSTO DE RENDA | I1: Inicio
B2: 2. RENDIMENTOS
B4: Registre todas as fontes de renda do ano-base, separando titular e dependentes.
B6: Categoria | C6: Fonte pagadora | D6: CNPJ/CPF da fonte | E6: Titular/Dep. | F6: Valor tributavel (R$) | G6: Rend. isento (R$) | H6: Imposto retido (R$) | I6: Comprovante
B7: Salario / CLT | C7: Empresa Exemplo LTDA | D7: 12.345.678/0001-99 | E7: Titular | F7: 54000 | G7: 0 | H7: 4200 | I7: Anexado
B8: Aposentadoria / Pensao (INSS) | C8: INSS | D8: 29.979.036/0001-40 | E8: Titular | F8: 0 | G8: 28000 | H8: 0 | I8: Recebido
B9: Alugueis | C9: Imovel Rua das Demonstracoes (aluguel) | E9: Titular | F9: 14400 | G9: 0 | H9: 0 | I9: Pendente
B32: TOTAL | F32: =SUM(F7:F31) | G32: =SUM(G7:G31) | H32: =SUM(H7:H31)
B34: Dados de exemplo sao ficticios. Preencha novas linhas dentro da tabela; os totais se atualizam automaticamente.

Sheet BENS E DIREITOS
B1: AGREGADOR DE IMPOSTO DE RENDA | H1: Inicio
B2: 3. BENS E DIREITOS
B4: Relacione os bens e direitos em 31/12. A variacao (atual - anterior) e calculada automaticamente.
B6: Grupo / Tipo | C6: Descricao do bem | D6: Localizacao / Instituicao | E6: Situacao 31/12 ANTERIOR (R$) | F6: Situacao 31/12 ATUAL (R$) | G6: Variacao (R$) | H6: Comprovante
B7: Imovel | C7: Apartamento 2 quartos (exemplo) | D7: Sao Paulo/SP | E7: 180000 | F7: 180000 | G7: =IF(AND(E7="",F7=""),"",IFERROR(F7-E7,"")) | H7: Anexado
B8: Veiculo | C8: Automovel popular 2019 | D8: Sao Paulo/SP | E8: 45000 | F8: 40000 | G8: =IF(AND(E8="",F8=""),"",IFERROR(F8-E8,"")) | H8: Recebido
B9: Conta corrente / poupanca | C9: Conta corrente | D9: 260 - Nubank | E9: 8000 | F9: 12500 | G9: =IF(AND(E9="",F9=""),"",IFERROR(F9-E9,"")) | H9: Pendente
G10: =IF(AND(E10="",F10=""),"",IFERROR(F10-E10,""))
G11: =IF(AND(E11="",F11=""),"",IFERROR(F11-E11,""))
G12: =IF(AND(E12="",F12=""),"",IFERROR(F12-E12,""))
G13: =IF(AND(E13="",F13=""),"",IFERROR(F13-E13,""))
G14: =IF(AND(E14="",F14=""),"",IFERROR(F14-E14,""))
G15: =IF(AND(E15="",F15=""),"",IFERROR(F15-E15,""))
G16: =IF(AND(E16="",F16=""),"",IFERROR(F16-E16,""))
G17: =IF(AND(E17="",F17=""),"",IFERROR(F17-E17,""))
G18: =IF(AND(E18="",F18=""),"",IFERROR(F18-E18,""))
G19: =IF(AND(E19="",F19=""),"",IFERROR(F19-E19,""))
G20: =IF(AND(E20="",F20=""),"",IFERROR(F20-E20,""))
G21: =IF(AND(E21="",F21=""),"",IFERROR(F21-E21,""))
... G31: =IF(AND(E31="",F31=""),"",IFERROR(F31-E31,""))
B32: TOTAL | E32: =SUM(E7:E31) | F32: =SUM(F7:F31) | G32: =SUM(G7:G31)
B34: Dados de exemplo sao ficticios. Preencha novas linhas dentro da tabela; os totais se atualizam automaticamente.

Sheet DIVIDAS E ONUS
B1: AGREGADOR DE IMPOSTO DE RENDA | H1: Inicio
B2: 4. DIVIDAS E ONUS
B4: Registre financiamentos, emprestimos e demais dividas com saldo em 31/12.
B6: Tipo | C6: Credor / Instituicao | D6: Descricao | E6: Saldo 31/12 ANTERIOR (R$) | F6: Saldo 31/12 ATUAL (R$) | G6: Amortizado no ano (R$) | H6: Comprovante
B7: Financiamento imobiliario | C7: 104 - Caixa Economica Federal | D7: Financiamento do apartamento | E7: 120000 | F7: 110000 | G7: =IF(AND(D7="",E7=""),"",IFERROR(D7-E7,"")) | H7: Anexado
B8: Financiamento de veiculo | C8: 341 - Itau Unibanco | D8: Financiamento do automovel | E8: 30000 | F8: 20000 | G8: =IF(AND(D8="",E8=""),"",IFERROR(D8-E8,"")) | H8: Pendente
G9: =IF(AND(D9="",E9=""),"",IFERROR(D9-E9,""))
G10: =IF(AND(D10="",E10=""),"",IFERROR(D10-E10,""))
G11: =IF(AND(D11="",E11=""),"",IFERROR(D11-E11,""))
G12: =IF(AND(D12="",E12=""),"",IFERROR(D12-E12,""))
G13: =IF(AND(D13="",E13=""),"",IFERROR(D13-E13,""))
G14: =IF(AND(D14="",E14=""),"",IFERROR(D14-E14,""))
G15: =IF(AND(D15="",E15=""),"",IFERROR(D15-E15,""))
G16: =IF(AND(D16="",E16=""),"",IFERROR(D16-E16,""))
G17: =IF(AND(D17="",E17=""),"",IFERROR(D17-E17,""))
G18: =IF(AND(D18="",E18=""),"",IFERROR(D18-E18,""))
G19: =IF(AND(D19="",E19=""),"",IFERROR(D19-E19,""))
G20: =IF(AND(D20="",E20=""),"",IFERROR(D20-E20,""))
... G26: =IF(AND(D26="",E26=""),"",IFERROR(D26-E26,""))
B27: TOTAL | E27: =SUM(E7:E26) | F27: =SUM(F7:F26) | G27: =SUM(G7:G26)
B29: Dados de exemplo sao ficticios. Preencha novas linhas dentro da tabela; os totais se atualizam automaticamente.

Sheet PAGAMENTOS
B1: AGREGADOR DE IMPOSTO DE RENDA | H1: Inicio
B2: 5. PAGAMENTOS / DESPESAS DEDUTIVEIS
B4: Registre despesas dedutiveis (medicas, educacao, previdencia, pensao) com comprovante.
B6: Categoria | C6: Beneficiario / Prestador | D6: CNPJ/CPF | E6: Titular/Dep. | F6: Valor pago (R$) | G6: Dedutivel? | H6: Comprovante
B7: Despesas medicas | C7: Clinica Exemplo | D7: 01.234.567/0001-00 | E7: Titular | F7: 3200 | G7: Sim | H7: Anexado
B8: Educacao | C8: Escola Modelo | D8: 09.876.543/0001-11 | E8: Dependente | F8: 9600 | G8: Sim | H8: Recebido
B9: Plano de saude | C9: Operadora Demonstracao | D9: 11.222.333/0001-44 | E9: Titular | F9: 7200 | G9: Sim | H9: Pendente
B32: TOTAL | F32: =SUM(F7:F31)
B34: Dados de exemplo sao ficticios. Preencha novas linhas dentro da tabela; os totais se atualizam automaticamente.

Sheet DEPENDENTES
B1: AGREGADOR DE IMPOSTO DE RENDA | F1: Inicio
B2: 6. DEPENDENTES
B4: Cadastre os dependentes declarados. CPF e obrigatorio para qualquer idade.
B6: Nome do dependente | C6: CPF | D6: Data de nascimento | E6: Grau de parentesco | F6: Observacoes
B7: Pedro Ficticio da Silva | C7: 222.333.444-05 | D7: 15/03/2015 | E7: Filho(a) | F7: Estudante
B8: Ana Ficticia da Silva | C8: 333.444.555-06 | D8: 20/07/2018 | E8: Filho(a)
B24: Dados de exemplo sao ficticios. Preencha novas linhas dentro da tabela; os totais se atualizam automaticamente.

Sheet DOCUMENTOS
B1: AGREGADOR DE IMPOSTO DE RENDA | G1: Inicio
B2: 7. DOCUMENTOS / COMPROVANTES
B4: Controle central dos comprovantes. Use a coluna Link para apontar o arquivo (nuvem/pasta).
B6: Documento | C6: Categoria | D6: Ano | E6: Status | F6: Observacao | G6: Link do arquivo
B7: Informe de rendimentos - Empresa Exemplo | C7: Rendimentos | D7: 2024 | E7: Anexado | F7: Fonte principal | G7: https://exemplo.com/informe.pdf
B8: Informe INSS | C8: Rendimentos | D8: 2024 | E8: Recebido | F8: Aposentadoria | G8: https://exemplo.com/inss.pdf
B9: Recibos medicos | C9: Pagamentos / Despesas | D9: 2024 | E9: Pendente | F9: Reunir recibos do ano
B10: Comprovante IPTU / imovel | C10: Bens e Direitos | D10: 2024 | E10: Solicitado | F10: Prefeitura
B34: Dados de exemplo sao ficticios. Preencha novas linhas dentro da tabela; os totais se atualizam automaticamente.

Sheet RESUMO
B1: AGREGADOR DE IMPOSTO DE RENDA | I1: Inicio
B2: 8. RESUMO (DASHBOARD)
B4: Visao consolidada das informacoes cadastradas. Os valores se atualizam automaticamente.
B6: TOTAL DE RENDIMENTOS | D6: IMPOSTO RETIDO NA FONTE | F6: TOTAL DE BENS (31/12) | H6: TOTAL DE DIVIDAS (31/12)
B7: =SUM(RENDIMENTOS!F7:F31)+SUM(RENDIMENTOS!G7:G31) | D7: =SUM(RENDIMENTOS!H7:H31) | F7: =SUM('BENS E DIREITOS'!F7:F31) | H7: =SUM('DIVIDAS E ONUS'!F7:F26)
B10: PATRIMONIO LIQUIDO | D10: DESPESAS DEDUTIVEIS | F10: DEPENDENTES | H10: DOCUMENTOS PENDENTES
B11: =SUM('BENS E DIREITOS'!F7:F31)-SUM('DIVIDAS E ONUS'!F7:F26) | D11: =SUM(PAGAMENTOS!F7:F31) | F11: =COUNTA(DEPENDENTES!B7:B21) | H11: =COUNTIF(DOCUMENTOS!E7:E31,"Pendente")+COUNTIF(DOCUMENTOS!E7:E31,"Solicitado")
B15: RENDIMENTOS POR CATEGORIA | G15: BENS POR GRUPO
B16: Categoria | E16: Valor (R$) | G16: Grupo | I16: Valor (R$)
B17: Salario / CLT | E17: =SUMIF(RENDIMENTOS!B7:B31,B17,RENDIMENTOS!F7:F31)+SUMIF(RENDIMENTOS!B7:B31,B17,RENDIMENTOS!G7:G31) | G17: Imovel | I17: =SUMIF('BENS E DIREITOS'!B7:B31,G17,'BENS E DIREITOS'!F7:F31)
B18: 13o salario | E18: =SUMIF(RENDIMENTOS!B7:B31,B18,RENDIMENTOS!F7:F31)+SUMIF(RENDIMENTOS!B7:B31,B18,RENDIMENTOS!G7:G31) | G18: Veiculo | I18: =SUMIF('BENS E DIREITOS'!B7:B31,G18,'BENS E DIREITOS'!F7:F31)
B19: Aposentadoria / Pensao (INSS) | E19: =SUMIF(RENDIMENTOS!B7:B31,B19,RENDIMENTOS!F7:F31)+SUMIF(RENDIMENTOS!B7:B31,B19,RENDIMENTOS!G7:G31) | G19: Conta corrente / poupanca | I19: =SUMIF('BENS E DIREITOS'!B7:B31,G19,'BENS E DIREITOS'!F7:F31)
B20: Pensao alimenticia recebida | E20: =SUMIF(RENDIMENTOS!B7:B31,B20,RENDIMENTOS!F7:F31)+SUMIF(RENDIMENTOS!B7:B31,B20,RENDIMENTOS!G7:G31) | G20: Aplicacao financeira | I20: =SUMIF('BENS E DIREITOS'!B7:B31,G20,'BENS E DIREITOS'!F7:F31)
B21: Trabalho autonomo / PJ | E21: =SUMIF(RENDIMENTOS!B7:B31,B21,RENDIMENTOS!F7:F31)+SUMIF(RENDIMENTOS!B7:B31,B21,RENDIMENTOS!G7:G31) | G21: Participacao societaria | I21: =SUMIF('BENS E DIREITOS'!B7:B31,G21,'BENS E DIREITOS'!F7:F31)
B22: Alugueis | E22: =SUMIF(RENDIMENTOS!B7:B31,B22,RENDIMENTOS!F7:F31)+SUMIF(RENDIMENTOS!B7:B31,B22,RENDIMENTOS!G7:G31) | G22: Criptoativo | I22: =SUMIF('BENS E DIREITOS'!B7:B31,G22,'BENS E DIREITOS'!F7:F31)
B23: Rendimentos de aplicacoes financeiras | E23: =SUMIF(RENDIMENTOS!B7:B31,B23,RENDIMENTOS!F7:F31)+SUMIF(RENDIMENTOS!B7:B31,B23,RENDIMENTOS!G7:G31) | G23: Bens moveis / Outros | I23: =SUMIF('BENS E DIREITOS'!B7:B31,G23,'BENS E DIREITOS'!F7:F31)
B24: Dividendos / Lucros | E24: =SUMIF(RENDIMENTOS!B7:B31,B24,RENDIMENTOS!F7:F31)+SUMIF(RENDIMENTOS!B7:B31,B24,RENDIMENTOS!G7:G31)
B25: Rendimentos recebidos do exterior | E25: =SUMIF(RENDIMENTOS!B7:B31,B25,RENDIMENTOS!F7:F31)+SUMIF(RENDIMENTOS!B7:B31,B25,RENDIMENTOS!G7:G31) | G25: CONTROLE DE DOCUMENTOS
B26: Outros rendimentos | E26: =SUMIF(RENDIMENTOS!B7:B31,B26,RENDIMENTOS!F7:F31)+SUMIF(RENDIMENTOS!B7:B31,B26,RENDIMENTOS!G7:G31) | G26: Cadastrados | I26: =COUNTA(DOCUMENTOS!B7:B31)
B27: Dashboard: totais calculados por SOMA, SOMASE (SUMIF) e CONT.SE/CONT.VALORES sobre as demais abas. | G27: Concluidos (Anexado/Recebido) | I27: =COUNTIF(DOCUMENTOS!E7:E31,"Anexado")+COUNTIF(DOCUMENTOS!E7:E31,"Recebido")
G28: Pendentes/Solicitados | I28: =COUNTIF(DOCUMENTOS!E7:E31,"Pendente")+COUNTIF(DOCUMENTOS!E7:E31,"Solicitado")
G29: % de conclusao | I29: =IFERROR((COUNTIF(DOCUMENTOS!E7:E31,"Anexado")+COUNTIF(DOCUMENTOS!E7:E31,"Recebido"))/COUNTA(DOCUMENTOS!B7:B31),0)

Sheet LISTAS
A1: TABELAS DE APOIO / LISTAS DE VALIDACAO
A2: Esta aba alimenta os menus suspensos (validacao de dados) das demais abas. Nao renomeie os cabecalhos. Voce pode acrescentar itens ao final de cada lista.
A4: SIM_NAO | B4: UF | C4: TITDEP | D4: CAT_REND | E4: GRUPO_BENS | F4: TIPO_DIVIDA | G4: CAT_PAG | H4: PARENTESCO | I4: STATUS_DOC | J4: CAT_DOC | K4: OCUPACAO | L4: BANCOS
A5: Sim | B5: AC | C5: Titular | D5: Salario / CLT | E5: Imovel | F5: Financiamento imobiliario | G5: Despesas medicas | H5: Conjuge / Companheiro(a) | I5: Pendente | J5: Dados Pessoais | K5: Empregado(a) CLT | L5: 1 - Banco do Brasil
A6: Nao | B6: AL | C6: Dependente | D6: 13o salario | E6: Veiculo | F6: Financiamento de veiculo | G6: Plano de saude | H6: Filho(a) | I6: Solicitado | J6: Rendimentos | K6: Servidor(a) publico(a) | L6: 33 - Banco Santander
B7: AP | D7: Aposentadoria / Pensao (INSS) | E7: Conta corrente / poupanca | F7: Emprestimo pessoal | G7: Educacao | H7: Enteado(a) | I7: Recebido | J7: Bens e Direitos | K7: Autonomo(a) / MEI | L7: 77 - Banco Inter
B8: AM | D8: Pensao alimenticia recebida | E8: Aplicacao financeira | F8: Cartao de credito | G8: Previdencia privada (PGBL) | H8: Pais / Avos / Bisavos | I8: Anexado | J8: Dividas | K8: Empresario(a) | L8: 104 - Caixa Economica Federal
B9: BA | D9: Trabalho autonomo / PJ | E9: Participacao societaria | F9: Consorcio | G9: Pensao alimenticia judicial | H9: Neto(a) / Bisneto(a) | I9: Nao se aplica | J9: Pagamentos / Despesas | K9: Aposentado(a) / Pensionista | L9: 208 - Banco BTG Pactual
B10: CE | D10: Alugueis | E10: Criptoativo | F10: Outras dividas | G10: Contribuicao INSS | H10: Irmao(a) | J10: Dependentes | K10: Estudante | L10: 212 - Banco Original
B11: DF | D11: Rendimentos de aplicacoes financeiras | E11: Bens moveis / Outros | G11: Doacoes incentivadas | H11: Menor sob guarda judicial | J11: Outros | K11: Outros | L11: 237 - Banco Bradesco
B12: ES | D12: Dividendos / Lucros | G12: Outras despesas | H12: Outros | L12: 260 - Nubank
B13: GO | D13: Rendimentos recebidos do exterior | L13: 290 - PagBank
B14: MA | D14: Outros rendimentos | L14: 336 - C6 Bank
B15: MT | L15: 341 - Itau Unibanco
B16: MS | L16: 380 - PicPay
B17: MG | L17: 422 - Banco Safra
B18: PA | L18: 748 - Sicredi
B19: PB | L19: 102 - XP Investimentos
B20: PR | L20: Outros
B21: PE
B22: PI
B23: RJ
B24: RN
B25: RS
B26: RO
B27: RR
B28: SC
B29: SP
B30: SE
B31: TO
